agix/__init__.py
agix/config.py
agix/adapters/__init__.py
agix/adapters/base.py
agix/adapters/art/__init__.py
agix/adapters/art/adapter.py
agix/adapters/biology/__init__.py
agix/adapters/biology/adapter.py
agix/adapters/education/__init__.py
agix/adapters/education/adapter.py
agix/adapters/gpt/__init__.py
agix/adapters/gpt/adapter.py
agix/adapters/service/__init__.py
agix/adapters/service/adapter.py
agix/agents/__init__.py
agix/agents/affective_npc.py
agix/agents/base.py
agix/agents/genetic.py
agix/agents/heuristic_genetic.py
agix/agents/narrative.py
agix/agents/neuromorphic.py
agix/agents/universal.py
agix/architecture/__init__.py
agix/architecture/ameta.py
agix/autoagent/__init__.py
agix/autoagent/loop.py
agix/autonarrative/__init__.py
agix/autonarrative/autonarrative_core.py
agix/cli/__init__.py
agix/cli/main.py
agix/cli/qualia_shell.py
agix/cli/repl.py
agix/cli/commands/__init__.py
agix/cli/commands/autoagent.py
agix/cli/commands/evaluate.py
agix/cli/commands/experiment.py
agix/cli/commands/hub.py
agix/cli/commands/inspect.py
agix/cli/commands/razonar.py
agix/cli/commands/serve.py
agix/cli/commands/simulate.py
agix/cli/commands/train_ml.py
agix/control/__init__.py
agix/control/controller_core.py
agix/control/policy_optimization.py
agix/control/reflexive_logic.py
agix/control/strategy_evaluator.py
agix/dashboard/__init__.py
agix/dashboard/server.py
agix/emotion/__init__.py
agix/emotion/emotion_simulator.py
agix/environments/__init__.py
agix/environments/env_base.py
agix/environments/robotics.py
agix/environments/video_game.py
agix/environments/vr.py
agix/ethics/__init__.py
agix/ethics/alignment.py
agix/ethics/ethical_dilemma_simulator.py
agix/ethics/frameworks.py
agix/ethics/moral_emotions.py
agix/evaluation/__init__.py
agix/evaluation/ethics.py
agix/evaluation/feedback.py
agix/evaluation/harmony.py
agix/evaluation/learning_quality.py
agix/evaluation/metrics.py
agix/evaluation/narrative_compression.py
agix/evaluation/reasoning_metrics.py
agix-1.7.0.dist-info/licenses/LICENSE.md
agix-1.7.0.dist-info/METADATA
agix-1.7.0.dist-info/WHEEL
agix-1.7.0.dist-info/entry_points.txt
agix-1.7.0.dist-info/top_level.txt
agix-1.7.0.dist-info/RECORD
