Metadata-Version: 2.4
Name: agix
Version: 1.7.0
Summary: Experimental AGI framework with neuro-symbolic reasoning, evolutionary agents and plastic learning
Author-email: Adolfo <adolfogonzal@gmail.com>
License-Expression: MIT
Keywords: AGI,neuro-symbolic,evolution,machine-learning,reasoning
Classifier: Development Status :: 3 - Alpha
Classifier: Programming Language :: Python :: 3.10
Classifier: Programming Language :: Python :: 3.11
Classifier: Programming Language :: Python :: 3.12
Classifier: Intended Audience :: Developers
Classifier: Topic :: Scientific/Engineering :: Artificial Intelligence
Requires-Python: >=3.10
License-File: LICENSE.md
Requires-Dist: numpy>=1.22
Requires-Dist: scipy>=1.9
Requires-Dist: matplotlib>=3.5
Requires-Dist: networkx>=3.0
Requires-Dist: fastapi>=0.115
Requires-Dist: uvicorn>=0.34
Requires-Dist: flet>=0.28
Provides-Extra: ml
Requires-Dist: scikit-learn; extra == "ml"
Provides-Extra: data
Requires-Dist: pandas; extra == "data"
Dynamic: license-file
